Metadata-Version: 1.1
Name: djangorestframework-swagger
Version: 0.2.2
Summary: Swagger UI for your Django REST Framework API
Home-page: https://github.com/ivangeorgiev/django-rest-framework-swagger
Author: Ivan Georgiev
Author-email: ivan.georgiev@gmail.com
License: BSD
Platform: UNKNOWN
Classifier: Development Status :: 2 - Pre-Alpha
Classifier: Environment :: Web Environment
Classifier: Framework :: Django
Classifier: Intended Audience :: Developers
Classifier: License :: OSI Approved :: BSD License
Classifier: Operating System :: OS Independent
Classifier: Natural Language :: English
Classifier: Programming Language :: Python :: 2
Classifier: Programming Language :: Python :: 2.7
Classifier: Programming Language :: Python :: 3
Classifier: Programming Language :: Python :: 3.3
Classifier: Programming Language :: Python :: 3.4
Classifier: Topic :: Internet :: WWW/HTTP
